AUTHORS.md
HISTORY.md
LICENSE
minos/auth_credential/__init__.py
minos/auth_credential/__main__.py
minos/auth_credential/cli.py
minos/auth_credential/config.py
minos/auth_credential/cryptography/cryptography.py
minos/auth_credential/database/models.py
minos/auth_credential/exceptions.py
minos/auth_credential/handler.py
minos/auth_credential/launchers.py
minos/auth_credential/service.py
minos_auth_credential-0.1.0.dist-info/entry_points.txt
minos_auth_credential-0.1.0.dist-info/LICENSE
minos_auth_credential-0.1.0.dist-info/WHEEL
minos_auth_credential-0.1.0.dist-info/METADATA
minos_auth_credential-0.1.0.dist-info/RECORD
