Metadata-Version: 2.1
Name: minos-auth-credential
Version: 0.1.0
Summary: Minos Boilerplate contains all the boilerplate you need to create a Minos Python package.
Home-page: https://clariteia.com
License: MIT
Keywords: clariteia,minos,microservice,saga
Author: Clariteia Devs
Author-email: devs@clariteia.com
Requires-Python: >=3.9,<4.0
Classifier: Development Status :: 2 - Pre-Alpha
Classifier: Intended Audience :: Developers
Classifier: License :: OSI Approved :: MIT License
Classifier: Natural Language :: English
Classifier: Programming Language :: Python :: 3
Classifier: Programming Language :: Python :: 3.10
Classifier: Programming Language :: Python :: 3.9
Requires-Dist: PyYAML (>=6.0,<7.0)
Requires-Dist: SQLAlchemy (==1.4.22)
Requires-Dist: aiohttp-middlewares (>=1.1.0,<2.0.0)
Requires-Dist: aiomisc (>=15.2.16,<16.0.0)
Requires-Dist: cached-property (>=1.5.2,<2.0.0)
Requires-Dist: passlib (>=1.7.4,<2.0.0)
Requires-Dist: psycopg2 (>=2.9.3,<3.0.0)
Requires-Dist: typer (>=0.3.2,<0.4.0)
Requires-Dist: uuid (>=1.30,<2.0)
Project-URL: Repository, https://github.com/clariteia/minos_auth_credential
